piweatherrock/webconfig/__init__.py
piweatherrock/webconfig/html/config.html
piweatherrock/webconfig/html/serialize_script.js
piweatherrock/webconfig/html/style.css
piweatherrock/webconfig/icons/bg.png
piweatherrock/webconfig/icons/256/chancetstorms.png
piweatherrock_webconfig-1.5.0.data/scripts/pwr-webconfig
piweatherrock_webconfig-1.5.0.dist-info/LICENSE
piweatherrock_webconfig-1.5.0.dist-info/METADATA
piweatherrock_webconfig-1.5.0.dist-info/WHEEL
piweatherrock_webconfig-1.5.0.dist-info/top_level.txt
piweatherrock_webconfig-1.5.0.dist-info/RECORD
