Metadata-Version: 2.1
Name: piweatherrock-webconfig
Version: 1.5.0
Summary: Provides a web interface for configuring PiWeatherRock
Home-page: https://github.com/genebean/piweatherrock-webconfig
Author: Gene Liverman
Author-email: gene@technicalissues.us
License: MIT
Platform: UNKNOWN
Classifier: License :: OSI Approved :: MIT License
Requires-Python: >=3.6
Requires-Dist: cherrypy
